socketio/__init__.py
socketio/defaultjson.py
socketio/handler.py
socketio/mixins.py
socketio/namespace.py
socketio/packet.py
socketio/policyserver.py
socketio/sdjango.py
socketio/server.py
socketio/sgunicorn.py
socketio/transports.py
socketio/virtsocket.py
gevent_socketio_py3-1.0.1.dist-info/AUTHORS
gevent_socketio_py3-1.0.1.dist-info/LICENSE
gevent_socketio_py3-1.0.1.dist-info/METADATA
gevent_socketio_py3-1.0.1.dist-info/WHEEL
gevent_socketio_py3-1.0.1.dist-info/entry_points.txt
gevent_socketio_py3-1.0.1.dist-info/top_level.txt
gevent_socketio_py3-1.0.1.dist-info/RECORD
